{
  "variants": {
    "axis=x,melted=false": {
      "model": "waxed:block/olive_wax_pillar_horizontal",
      "x": 90,
      "y": 90
    },
    "axis=y,melted=false": {
      "model": "waxed:block/olive_wax_pillar"
    },
    "axis=z,melted=false": {
      "model": "waxed:block/olive_wax_pillar_horizontal",
      "x": 90
    },
    "axis=x,melted=true": {
      "model": "waxed:block/melted_olive_wax_pillar_horizontal",
      "x": 90,
      "y": 90
    },
    "axis=y,melted=true": {
      "model": "waxed:block/melted_olive_wax_pillar"
    },
    "axis=z,melted=true": {
      "model": "waxed:block/melted_olive_wax_pillar_horizontal",
      "x": 90
    }
  }
}